{"json": false, "savejson": null, "inputdir": "/share/incoming", "outputdir": "/share/outgoing", "inputmeta": null, "saveinputmeta": true, "saveoutputmeta": true, "version": false, "meta": false, "verbosity": "0", "man": false, "csv_file": "", "iname": "brainmask.mgz", "oname": "aparc.DKTatlas+aseg.deep.mgz", "order": 1, "search_tag": "recon-of-SAG-anon-dcm/mri/", "logfile": "deep-seg.log", "network_sagittal_path": "../checkpoints/Sagittal_Weights_FastSurferCNN/ckpts/Epoch_30_training_state.pkl", "network_coronal_path": "../checkpoints/Coronal_Weights_FastSurferCNN/ckpts/Epoch_30_training_state.pkl", "network_axial_path": "../checkpoints/Axial_Weights_FastSurferCNN/ckpts/Epoch_30_training_state.pkl", "cleanup": "true", "no_cuda": false, "batch_size": 8, "simple_run": false, "run_parallel": false}