{"status": true, "info": {"pushPath": {"return": {"d_ret": {"host-data": {"stdout": {"compress": {"local": {"zip": {"fileProcessed": "9a45e744-f204-4dfe-a063-ed7ef03fecfa.zip", "filesInZip": 43, "filesize": "37,730,699", "localFSsize": 38279925, "msg": "zip operation successful", "path": "/chris/feed_1/pl-dircopy_1/pl-fshack_4/data", "status": true, "timestamp": "2020-10-08 19:23:11.462573", "zipmode": "w"}}, "msg": "File written successfully!", "remoteServer": {"User-agent": "PycURL/7.43.0.6 libcurl/7.68.0 OpenSSL/1.1.1f zlib/1.2.11 brotli/1.0.7 libidn2/2.2.0 libpsl/0.21.0 (+libidn2/2.2.0) libssh/0.9.3/openssl/zlib nghttp2/1.40.0 librtmp/2.3", "msg": "File written successfully!", "postop": {"incomingPath": "/hostFS/storeBase/key-chris-jid-5/incoming", "op": "plugin", "outgoingPath": "/hostFS/storeBase/key-chris-jid-5/outgoing", "shareDir": "/hostFS/storeBase/key-chris-jid-5/", "status": true, "timestamp": "2020-10-08 19:23:13.009431", "tmpPath": "/tmp/36da3674-89de-4da0-b31b-c12d43689c46"}, "status": true, "write": {"file": "/hostFS/storeBase/key-chris-jid-5/", "msg": "File written successfully!", "status": true, "timestamp": "2020-10-08 19:23:12.933055"}}, "status": true}, "localCheck": {"check": {"action": "pushPath", "dir": "/chris/feed_1/pl-dircopy_1/pl-fshack_4/data", "isdir": true, "isfile": false, "msg": "", "status": true}, "msg": "Check on local path successful.", "status": true, "timestamp": "2020-10-08 19:23:09.803247"}, "msg": "File written successfully!", "remoteCheck": {"msg": "Check on remote path successful.", "response": {"data": "200 OK\r\nContent-Type: text/html; charset=UTF-8\r\nContent-Length: 95\r\n\r\n{\"status\": true, \"isfile\": false, \"isswiftstore\": false, \"isdir\": false, \"createdNewDir\": true}", "status": true}, "size": "2", "status": true, "timestamp": "2020-10-08 19:23:09.814675"}, "status": true}}}, "serviceName": "host", "status": true}, "status": true}, "compute": {"return": {"RESTheader": "POST /api/v1/cmd/ HTTP/1.1\r", "RESTverb": "POST", "action": "status", "client_json_len": 81, "client_json_payload": "{\"payload\": {\"action\": \"status\", \"meta\": {\"key\": \"jid\", \"value\": \"chris-jid-5\"}}}", "d_ret": {"0.container": {"jobRoot": "20201008192317.641625_bbc191c5-d1b6-497c-9edb-1e535d0f459c", "tree": {"20201008192317.641625_bbc191c5-d1b6-497c-9edb-1e535d0f459c": {"container": {"manager": {"app": "swarm.py", "env": {"meta-store": "key", "serviceName": "chris-jid-5", "serviceType": "docker", "shareDir": "/hostFS/storeBase/key-chris-jid-5/"}, "image": "fnndsc/swarm"}, "target": {"cmdParse": false, "execshell": "python3", "image": "fnndsc/pl-fastsurfer_inference", "selfexec": "fastsurfer_inference.py", "selfpath": "/usr/src/fastsurfer_inference"}}}}}, "0.end": {"jobRoot": "20201008192317.641625_bbc191c5-d1b6-497c-9edb-1e535d0f459c", "returncode": [0]}, "0.start": {"jobRoot": "20201008192317.641625_bbc191c5-d1b6-497c-9edb-1e535d0f459c", "startTrigger": [true]}, "l_logs": ["\n / _|        | |                 / _|        (_)      / _|                            \n| |_ __ _ ___| |_ ___ _   _ _ __| |_ ___ _ __ _ _ __ | |_ ___ _ __ ___ _ __   ___ ___ \n|  _/ _` / __| __/ __| | | | '__|  _/ _ \\ '__| | '_ \\|  _/ _ \\ '__/ _ \\ '_ \\ / __/ _ | || (_| \\__ \\ |_\\__ \\ |_| | |  | ||  __/ |  | | | | | ||  __/ | |  __/ | | | (_|  __/\n|_| \\__,_|___/\\__|___/\\__,_|_|  |_| \\___|_|  |_|_| |_|_| \\___|_|  \\___|_| |_|\\___\\___|\n                                        ______                                        \n                                       |______|    \n    \n\nVersion: 0.1\nTotal Dataset Size is 0\n"], "l_status": ["finishedSuccessfully"], "status": true}, "meta": {"key": "jid", "value": "chris-jid-5"}, "path": "/api/v1/cmd", "payloadsize": 81, "receivedByServer": ["POST /api/v1/cmd/ HTTP/1.1\r", "Host: 172.20.0.3:5010\r", "User-Agent: PycURL/7.43.0.6 libcurl/7.68.0 OpenSSL/1.1.1f zlib/1.2.11 brotli/1.0.7 libidn2/2.2.0 libpsl/0.21.0 (+libidn2/2.2.0) libssh/0.9.3/openssl/zlib nghttp2/1.40.0 librtmp/2.3\r", "Accept: */*\r", "Authorization: bearer password\r", "Mode: control\r", "Content-Length: 81\r", "Content-Type: application/x-www-form-urlencoded\r", "\r", "{\"payload\": {\"action\": \"status\", \"meta\": {\"key\": \"jid\", \"value\": \"chris-jid-5\"}}}"], "status": true}, "status": true, "submit": {"d_ret": {"host-computeRequest": {"RESTheader": "POST /api/v1/cmd/ HTTP/1.1\r", "RESTverb": "POST", "action": "run", "client_json_len": 798, "client_json_payload": "{\"payload\": {\"action\": \"run\", \"meta\": {\"cmd\": \"python3 /usr/src/fastsurfer_inference/fastsurfer_inference.py /share/incoming /share/outgoing --saveinputmeta --saveoutputmeta --in_name brainmask.mgz --t recon-of-SAG-anon-nii/mri/ --clean true\", \"threaded\": true, \"auid\": \"chris\", \"jid\": \"chris-jid-5\", \"number_of_workers\": \"1\", \"cpu_limit\": \"1000\", \"memory_limit\": \"200\", \"gpu_limit\": \"0\", \"container\": {\"target\": {\"image\": \"fnndsc/pl-fastsurfer_inference\", \"cmdParse\": false, \"selfexec\": \"fastsurfer_inference.py\", \"selfpath\": \"/usr/src/fastsurfer_inference\", \"execshell\": \"python3\"}, \"manager\": {\"image\": \"fnndsc/swarm\", \"app\": \"swarm.py\", \"env\": {\"meta-store\": \"key\", \"serviceType\": \"docker\", \"shareDir\": \"/hostFS/storeBase/key-chris-jid-5/\", \"serviceName\": \"chris-jid-5\"}}}, \"service\": \"host\"}}}", "meta": {"auid": "chris", "cmd": "python3 /usr/src/fastsurfer_inference/fastsurfer_inference.py /share/incoming /share/outgoing --saveinputmeta --saveoutputmeta --in_name brainmask.mgz --t recon-of-SAG-anon-nii/mri/ --clean true", "container": {"manager": {"app": "swarm.py", "env": {"meta-store": "key", "serviceName": "chris-jid-5", "serviceType": "docker", "shareDir": "/hostFS/storeBase/key-chris-jid-5/"}, "image": "fnndsc/swarm"}, "target": {"cmdParse": false, "execshell": "python3", "image": "fnndsc/pl-fastsurfer_inference", "selfexec": "fastsurfer_inference.py", "selfpath": "/usr/src/fastsurfer_inference"}}, "cpu_limit": "1000", "gpu_limit": "0", "jid": "chris-jid-5", "memory_limit": "200", "number_of_workers": "1", "service": "host", "threaded": true}, "path": "/api/v1/cmd", "payloadsize": 798, "receivedByServer": ["POST /api/v1/cmd/ HTTP/1.1\r", "Host: 172.20.0.3:5010\r", "User-Agent: PycURL/7.43.0.6 libcurl/7.68.0 OpenSSL/1.1.1f zlib/1.2.11 brotli/1.0.7 libidn2/2.2.0 libpsl/0.21.0 (+libidn2/2.2.0) libssh/0.9.3/openssl/zlib nghttp2/1.40.0 librtmp/2.3\r", "Accept: */*\r", "Authorization: bearer password\r", "Mode: control\r", "Content-Length: 798\r", "Content-Type: application/x-www-form-urlencoded\r", "\r", "{\"payload\": {\"action\": \"run\", \"meta\": {\"cmd\": \"python3 /usr/src/fastsurfer_inference/fastsurfer_inference.py /share/incoming /share/outgoing --saveinputmeta --saveoutputmeta --in_name brainmask.mgz --t recon-of-SAG-anon-nii/mri/ --clean true\", \"threaded\": true, \"auid\": \"chris\", \"jid\": \"chris-jid-5\", \"number_of_workers\": \"1\", \"cpu_limit\": \"1000\", \"memory_limit\": \"200\", \"gpu_limit\": \"0\", \"container\": {\"target\": {\"image\": \"fnndsc/pl-fastsurfer_inference\", \"cmdParse\": false, \"selfexec\": \"fastsurfer_inference.py\", \"selfpath\": \"/usr/src/fastsurfer_inference\", \"execshell\": \"python3\"}, \"manager\": {\"image\": \"fnndsc/swarm\", \"app\": \"swarm.py\", \"env\": {\"meta-store\": \"key\", \"serviceType\": \"docker\", \"shareDir\": \"/hostFS/storeBase/key-chris-jid-5/\", \"serviceName\": \"chris-jid-5\"}}}, \"service\": \"host\"}}}"], "status": true}}, "serviceName": "host", "status": true}}, "pullPath": {"return": {"d_ret": {"host-data": {"stdout": {"compress": {"localOp": {"move": {"msg": "Multiple file move successful.", "status": true}, "stream": {"fileWritten": "/tmp/unpack-5176bc8a-22cf-4679-836d-9e29bd41253a/5176bc8a-22cf-4679-836d-9e29bd41253a.zip", "filesize": "1,045", "msg": "Write successful.", "status": true, "timestamp": "2020-10-08 19:23:29.403542"}, "unzip": {"fileProcessed": "/tmp/unpack-5176bc8a-22cf-4679-836d-9e29bd41253a/5176bc8a-22cf-4679-836d-9e29bd41253a.zip", "filesInZip": 2, "filesize": "1,045", "localFSsize": 1854, "msg": "unzip operation successful", "path": "/tmp/unpack-5176bc8a-22cf-4679-836d-9e29bd41253a", "status": true, "timestamp": "2020-10-08 19:23:29.406829", "zipmode": "r"}}, "msg": "Multiple file move successful.", "remoteServer": {"msg": "PULL successful", "response": "<truncated>", "size": "2", "status": true, "timestamp": "2020-10-08 19:23:29.400808"}, "status": true}, "localCheck": {"check": {"action": "pullPath", "dir": "chris/feed_1/pl-dircopy_1/pl-fshack_4/pl-fastsurfer_inference_5", "isdir": true, "isfile": false, "msg": "", "status": true}, "msg": "Check on local path successful.", "status": true, "timestamp": "2020-10-08 19:23:29.317883"}, "msg": "Multiple file move successful.", "remoteCheck": {"msg": "Check on remote path successful.", "response": {"data": "200 OK\r\nContent-Type: text/html; charset=UTF-8\r\nContent-Length: 95\r\n\r\n{\"status\": true, \"isfile\": false, \"isswiftstore\": false, \"isdir\": true, \"createdNewDir\": false}", "status": true}, "size": "2", "status": true, "timestamp": "2020-10-08 19:23:29.349871"}, "status": true}}}, "serviceName": "host", "status": true}, "status": true}, "swiftPut": {"useSwift": true, "d_swift_ls": {"status": true, "objectDict": [{"hash": "a175465652ce013eb70d9509f7af494e", "last_modified": "2020-10-08T19:23:32.378630", "bytes": 807, "name": "chris/feed_1/pl-dircopy_1/pl-fshack_4/pl-fastsurfer_inference_5/data/input.meta.json", "content_type": "application/json"}, {"hash": "99914b932bd37a50b983c5e7c90ae93b", "last_modified": "2020-10-08T19:23:32.363150", "bytes": 2, "name": "chris/feed_1/pl-dircopy_1/pl-fshack_4/pl-fastsurfer_inference_5/data/output.meta.json", "content_type": "application/json"}], "lsList": ["chris/feed_1/pl-dircopy_1/pl-fshack_4/pl-fastsurfer_inference_5/data/input.meta.json", "chris/feed_1/pl-dircopy_1/pl-fshack_4/pl-fastsurfer_inference_5/data/output.meta.json"], "fullPath": "chris/feed_1/pl-dircopy_1/pl-fshack_4/pl-fastsurfer_inference_5/data"}, "d_swiftstore": {"status": true, "d_create": {"status": true, "d_result": {"l_fileFS": ["chris/feed_1/pl-dircopy_1/pl-fshack_4/pl-fastsurfer_inference_5/data/output.meta.json", "chris/feed_1/pl-dircopy_1/pl-fshack_4/pl-fastsurfer_inference_5/data/input.meta.json"]}}, "d_put": {"status": true, "d_result": {"l_fileStore": ["chris/feed_1/pl-dircopy_1/pl-fshack_4/pl-fastsurfer_inference_5/data/output.meta.json", "chris/feed_1/pl-dircopy_1/pl-fshack_4/pl-fastsurfer_inference_5/data/input.meta.json"]}}, "waitPoll": 0, "filesPushed": 2, "filesAccessible": 2}, "status": true}}}